princeapi/__init__.py
princeapi/api.py
prince_api-0.0.6.dist-info/LICENSE
prince_api-0.0.6.dist-info/METADATA
prince_api-0.0.6.dist-info/WHEEL
prince_api-0.0.6.dist-info/top_level.txt
prince_api-0.0.6.dist-info/RECORD
