Metadata-Version: 2.1
Name: prince-api
Version: 0.0.6
Summary: A Project Made To Centralize Various APIs 📖 No Authorization Needed :)
Home-page: https://github.com/NotReallyPrince/Prince-Api
Author: NotReallyPrince
Author-email: princebots3011@gmail.com
License: MIT
Project-URL: Tracker, https://github.com/NotReallyPrince/Prince-API/issues
Project-URL: Community, https://t.me/PrincexUpdates
Project-URL: Source, https://github.com/NotReallyPrince/Prince-API
Project-URL: Documentation, https://docs.prince-api.tk
Keywords: Prince-Api,python-pakage,api,Prince
Classifier: Development Status :: 5 - Production/Stable
Classifier: Intended Audience :: Developers
Classifier: License :: OSI Approved :: MIT License
Classifier: Programming Language :: Python
Classifier: Programming Language :: Python :: 3
Classifier: Programming Language :: Python :: 3.7
Classifier: Programming Language :: Python :: 3.8
Classifier: Programming Language :: Python :: 3.9
Classifier: Programming Language :: Python :: 3.10
Classifier: Programming Language :: Python :: 3.11
License-File: LICENSE
Requires-Dist: requests (>=2.28.1)
